README.md
setup.py
hkh_dev_package_5.egg-info/PKG-INFO
hkh_dev_package_5.egg-info/SOURCES.txt
hkh_dev_package_5.egg-info/dependency_links.txt
hkh_dev_package_5.egg-info/entry_points.txt
hkh_dev_package_5.egg-info/namespace_packages.txt
hkh_dev_package_5.egg-info/requires.txt
hkh_dev_package_5.egg-info/top_level.txt
orangecontrib/__init__.py
orangecontrib/dev/__init__.py
orangecontrib/dev/widgets/Chatbot.py
orangecontrib/dev/widgets/DocumentEater.py
orangecontrib/dev/widgets/EmbeddingsCreation.py
orangecontrib/dev/widgets/LanguageModel.py
orangecontrib/dev/widgets/MetManagement.py
orangecontrib/dev/widgets/TextPreprocessing.py
orangecontrib/dev/widgets/VarManagement.py
orangecontrib/dev/widgets/WrapMessageBox.py
orangecontrib/dev/widgets/__init__.py
orangecontrib/dev/widgets/goto.py
orangecontrib/dev/widgets/orange_sub_workflow.py
orangecontrib/dev/widgets/shared_functions.py
orangecontrib/dev/widgets/shared_variables.py
orangecontrib/dev/widgets/subworkflow_input.py
orangecontrib/dev/widgets/subworkflow_output.py
orangecontrib/dev/widgets/icons/Chatbot.svg
orangecontrib/dev/widgets/icons/DocumentEater.svg
orangecontrib/dev/widgets/icons/Embeddings.svg
orangecontrib/dev/widgets/icons/LanguageModel.svg
orangecontrib/dev/widgets/icons/Logo_HKH.svg
orangecontrib/dev/widgets/icons/TextPreprocessing.svg
orangecontrib/dev/widgets/icons/goto.png
orangecontrib/dev/widgets/icons/jcm_open_file_resize_alpha_channel.png
orangecontrib/dev/widgets/icons/subworkflow_output.png
orangecontrib/dev/widgets/kernel_function/Table_management.py
orangecontrib/dev/widgets/kernel_function/Utils_box.py
orangecontrib/dev/widgets/kernel_function/supp_moi_bis.tab
orangecontrib/dev/widgets/kernel_function/supp_moi_bis_permutation_tototo.tab
orangecontrib/dev/widgets/kernel_function/zoubida.dada
orangecontrib/dev/widgets/kernel_function/zoubida2.dada
orangecontrib/dev/widgets/widget_designer/goto.ui
orangecontrib/dev/widgets/widget_designer/load_tab.ui
orangecontrib/dev/widgets/widget_designer/orange_sub_workflow.ui
orangecontrib/dev/widgets/widget_designer/subworkflow_input_ui.ui
orangecontrib/dev/widgets/widget_designer/subworkflow_output_ui.ui